continuum_mechanics/__init__.py
continuum_mechanics/solids.py
continuum_mechanics/tensor.py
continuum_mechanics/vector.py
continuum_mechanics/visualization.py
continuum_mechanics-0.2.2.dist-info/AUTHORS.rst
continuum_mechanics-0.2.2.dist-info/LICENSE
continuum_mechanics-0.2.2.dist-info/METADATA
continuum_mechanics-0.2.2.dist-info/WHEEL
continuum_mechanics-0.2.2.dist-info/top_level.txt
continuum_mechanics-0.2.2.dist-info/RECORD
