Metadata-Version: 2.1
Name: continuum-mechanics
Version: 0.2.2
Summary: Utilities for doing calculations in continuum mechanics.
Home-page: https://github.com/nicoguaro/continuum_mechanics
Author: Nicolás Guarín-Zapata
Author-email: nicoguarin@gmail.com
License: MIT license
Keywords: continuum_mechanics
Platform: UNKNOWN
Classifier: Development Status :: 4 - Beta
Classifier: Intended Audience :: Developers
Classifier: License :: OSI Approved :: MIT License
Classifier: Natural Language :: English
Classifier: Programming Language :: Python :: 3
Classifier: Programming Language :: Python :: 3.7
Classifier: Programming Language :: Python :: 3.8
Classifier: Programming Language :: Python :: 3.9
Requires-Dist: sympy (>=1.3)
Requires-Dist: matplotlib (>=3)
Requires-Dist: numpy
Requires-Dist: scipy
